quayside/__init__.py
quayside/__main__.py
quayside/app.py
quayside/cli.py
quayside/default.yaml
quayside-0.1.post1.dist-info/LICENCE.md
quayside-0.1.post1.dist-info/METADATA
quayside-0.1.post1.dist-info/WHEEL
quayside-0.1.post1.dist-info/entry_points.txt
quayside-0.1.post1.dist-info/top_level.txt
quayside-0.1.post1.dist-info/RECORD
